flagpypi/__init__.py
flagpypi/main.py
flagpypi-5.7.2.dist-info/METADATA
flagpypi-5.7.2.dist-info/WHEEL
flagpypi-5.7.2.dist-info/top_level.txt
flagpypi-5.7.2.dist-info/RECORD
