Metadata-Version: 2.1
Name: flagpypi
Version: 5.7.2
Summary: flag package
Author: John Doe
Author-email: john_doe@gmail.com
Keywords: python package
Classifier: Development Status :: 3 - Alpha
Classifier: Intended Audience :: Education
Classifier: Programming Language :: Python :: 2
Classifier: Programming Language :: Python :: 3
Classifier: Operating System :: MacOS :: MacOS X
Classifier: Operating System :: Microsoft :: Windows
